task_tracker/__init__.py
task_tracker/_modidx.py
task_tracker/interfaces.py
task_tracker/trial_components.py
task_tracker/utils.py
task_tracking-0.0.2.dist-info/LICENSE
task_tracking-0.0.2.dist-info/METADATA
task_tracking-0.0.2.dist-info/WHEEL
task_tracking-0.0.2.dist-info/entry_points.txt
task_tracking-0.0.2.dist-info/top_level.txt
task_tracking-0.0.2.dist-info/RECORD
