Metadata-Version: 2.1
Name: task-tracking
Version: 0.0.2
Summary: A tool to track tasks, record audio and collect probands' demographics, designed to be used in a think-aloud approach
Home-page: https://github.com/KonKob/task-tracker
Author: Konstantin Kobel
Author-email: kobel.konstantin@web.de
License: Apache Software License 2.0
Keywords: nbdev jupyter notebook python
Classifier: Development Status :: 4 - Beta
Classifier: Intended Audience :: Developers
Classifier: Natural Language :: English
Classifier: Programming Language :: Python :: 3.7
Classifier: Programming Language :: Python :: 3.8
Classifier: Programming Language :: Python :: 3.9
Classifier: Programming Language :: Python :: 3.10
Classifier: License :: OSI Approved :: Apache Software License
Requires-Python: >=3.7
License-File: LICENSE
Requires-Dist: numpy
Requires-Dist: matplotlib
Requires-Dist: seaborn
Requires-Dist: ipywidgets
Requires-Dist: speechrecognition
Requires-Dist: scipy
Requires-Dist: sounddevice
Requires-Dist: jupyter
Requires-Dist: pandas
Provides-Extra: dev
Requires-Dist: nbdev ; extra == 'dev'
